geon-0.1.3.dist-info/WHEEL
geon-0.1.3.dist-info/entry_points.txt
geon-0.1.3.dist-info/METADATA
geon-0.1.3.dist-info/RECORD
geon-0.1.3.dist-info/licenses/LICENSE
geon/settings.py
geon/version.py
geon/app.py
geon/__init__.py
geon/algorithms/features.py
geon/algorithms/__init__.py
geon/resources/lasso.png
geon/resources/minus.png
geon/resources/bool_intersection.png
geon/resources/camera_left.png
geon/resources/tree_icon_field.png
geon/resources/wand.png
geon/resources/settings.png.png
geon/resources/region_growing.png
geon/resources/inspect_tool.png
geon/resources/.DS_Store
geon/resources/reggrow.png
geon/resources/deselect.png
geon/resources/camera_perspective_toggle.png
geon/resources/tree_icon_pointcloud.png
geon/resources/bool_overwrite.png
geon/resources/increase_point_size.png
geon/resources/camera_top.png
geon/resources/camera_front.png
geon/resources/camera_right.png
geon/resources/semantic_class_manager.png
geon/resources/bool_difference.png
geon/resources/show_all.png
geon/resources/annotate.png
geon/resources/hide.png
geon/resources/decrease_point_size.png
geon/resources/camera_back.png
geon/resources/load_segmentation.png
geon/resources/bool_exclusion.png
geon/resources/hide_selected.png
geon/resources/load.png
geon/resources/camera_isometric_toggle.png
geon/resources/label_semantics.png
geon/resources/label_instance.png
geon/resources/segmentation.png
geon/resources/bool_union.png
geon/resources/reggrow_settings.png
geon/resources/geon_icon.png
geon/resources/reset_view.png
geon/resources/wand_cursor.png
geon/resources/isolate.png
geon/resources/camera_bot.png
geon/resources/plus.png
geon/resources/classify_selection.png
geon/resources/svg/all_icons_dark.svg
geon/resources/logo/geometric-red.png
geon/rendering/util.py
geon/rendering/scene.py
geon/rendering/layer_registry.py
geon/rendering/pointcloud.py
geon/rendering/__init__.py
geon/rendering/base.py
geon/io/dataset.py
geon/io/serialization.py
geon/io/ply.py
geon/tools/visibility.py
geon/tools/tool_context.py
geon/tools/inspect.py
geon/tools/controller.py
geon/tools/lasso.py
geon/tools/camera.py
