Metadata-Version: 2.4
Name: geon
Version: 0.1.3
Summary: Interactive point cloud inspection and annotation tool.
Keywords: point-cloud,visualization,annotation,vtk,pyqt
Author: geon contributors
License-Expression: GPL-3.0-only
License-File: LICENSE
Classifier: Development Status :: 3 - Alpha
Classifier: Intended Audience :: Science/Research
Classifier: Programming Language :: Python :: 3
Classifier: Programming Language :: Python :: 3.10
Classifier: Programming Language :: Python :: 3.11
Classifier: Programming Language :: Python :: 3.12
Classifier: Operating System :: OS Independent
Classifier: Topic :: Scientific/Engineering :: Visualization
Requires-Python: >=3.10
Requires-Dist: numpy>=1.23
Requires-Dist: h5py>=3.8
Requires-Dist: PyQt6>=6.6
Requires-Dist: vtk>=9.2
Requires-Dist: plyfile>=0.8.1
Provides-Extra: dev
Requires-Dist: pytest>=7.4; extra == "dev"
Provides-Extra: test
Requires-Dist: pytest>=7.4; extra == "test"
